metabase_api/__init__.py
metabase_api/api_client.py
metabase_api/utils.py
multischema_metabase_dashboard_helper-0.1.0.dist-info/METADATA
multischema_metabase_dashboard_helper-0.1.0.dist-info/WHEEL
multischema_metabase_dashboard_helper-0.1.0.dist-info/entry_points.txt
multischema_metabase_dashboard_helper-0.1.0.dist-info/top_level.txt
multischema_metabase_dashboard_helper-0.1.0.dist-info/RECORD
