Metadata-Version: 2.1
Name: multischema-metabase-dashboard-helper
Version: 0.1.0
Summary: A Python client for duplicating Metabase dashboard for multi schemas
Requires-Dist: requests
